{"header": {"count": 1, "startDate": "2024-12-01", "startTime": "00:00:00", "endDate": "2024-12-30", "endTime": "23:59:59", "info": {"code": 8000000, "message": "Activity: Confidence: 27/30 Fitness: Confidence: 27/30 Heart: Confidence: 27/30, Heart BioAge confidence:  Sleep: Confidence: 27/30 Mental: Confidence: 27/30 ", "boostMessage": null}}, "data": [{"ts": 1735534800, "v": {"bioAge": 58, "bioAgeFraction": 57.63486934608102, "delta": -8, "deltaFraction": -8.365130653918982, "rating": "EXCEPTIONAL", "ratingFraction": "EXCEPTIONAL", "ageDiff": -8, "boost24": 50, "boostRating": "GOOD", "utilizationConfidence": null, "bioageConfidence": null, "profileAge": 66, "activityAge": {"bioAge": 61, "bioAgeFraction": 60.623733320304936, "delta": -5, "deltaFraction": -5.376266679695064, "rating": "EXCEPTIONAL", "ratingFraction": "EXCEPTIONAL", "ageDiff": -5, "boost24": 45, "boostRating": "GOOD", "minutes": {"bioAge": 60, "bioAgeFraction": 60.39851877079993, "delta": -6, "deltaFraction": -5.601481229200068, "rating": "EXCELLENT", "ratingFraction": "EXCELLENT"}, "sedentary": {"bioAge": 67, "bioAgeFraction": 67.04477424371598, "delta": 1, "deltaFraction": 1.0447742437159775, "rating": "EXCELLENT", "ratingFraction": "EXCELLENT"}, "rhr": {"bioAge": 65, "bioAgeFraction": 65.18044030578902, "delta": -1, "deltaFraction": -0.8195596942109802, "rating": "EXCEPTIONAL", "ratingFraction": "EXCEPTIONAL"}, "utilizationConfidence": 27, "bioageConfidence": "HIGH", "minutesBioAge": 60, "minutesAgeDiff": -6, "minutesRating": "EXCELLENT", "sedentaryBioAge": 67, "sedentaryAgeDiff": 1, "sedentaryRating": "EXCELLENT", "restingHeartRateBioAge": 65, "restingHeartRateAgeDiff": -1, "restingHeartRateRating": "EXCEPTIONAL"}, "fitnessAge": {"bioAge": 60, "bioAgeFraction": 59.67944523844047, "delta": -6, "deltaFraction": -6.320554761559528, "rating": "EXCEPTIONAL", "ratingFraction": "EXCEPTIONAL", "ageDiff": -6, "boost24": 7, "boostRating": "POOR", "vo2Max": {"bioAge": 63, "bioAgeFraction": 63.16715531641395, "delta": -3, "deltaFraction": -2.8328446835860532, "rating": "EXCEPTIONAL", "ratingFraction": "EXCEPTIONAL"}, "fitnessPoints": {"bioAge": 63, "bioAgeFraction": 62.512289922026525, "delta": -3, "deltaFraction": -3.4877100779734747, "rating": "EXCELLENT", "ratingFraction": "EXCEPTIONAL"}, "utilizationConfidence": 27, "bioageConfidence": "HIGH", "vo2MaxBioAge": 63, "vo2MaxAgeDiff": -3, "vo2MaxRating": "EXCEPTIONAL", "fitnessPointsBioAge": 63, "fitnessPointsAgeDiff": -3, "fitnessPointsRating": "EXCELLENT"}, "heartAge": {"bioAge": 48, "bioAgeFraction": 47.78426820292237, "delta": -18, "deltaFraction": -18.21573179707763, "rating": "EXCEPTIONAL", "ratingFraction": "EXCEPTIONAL", "ageDiff": -18, "boost24": 59, "boostRating": "GOOD", "sdnn": {"bioAge": 64, "bioAgeFraction": 64.33650621557878, "delta": -2, "deltaFraction": -1.6634937844212203, "rating": "GOOD", "ratingFraction": "GOOD"}, "rmssd": {"bioAge": 66, "bioAgeFraction": 65.61309060271027, "delta": 0, "deltaFraction": -0.3869093972897275, "rating": "GOOD", "ratingFraction": "EXCELLENT"}, "hr": {"bioAge": 56, "bioAgeFraction": 55.60925864254891, "delta": -10, "deltaFraction": -10.390741357451091, "rating": "EXCELLENT", "ratingFraction": "EXCELLENT"}, "hrv": {"bioAge": 52, "bioAgeFraction": 51.892343956298056, "delta": -14, "deltaFraction": -14.107656043701944, "rating": "EXCEPTIONAL", "ratingFraction": "EXCEPTIONAL"}, "pwf": {"bioAge": 46, "bioAgeFraction": 45.8007632931662, "delta": -20, "deltaFraction": -20.1992367068338, "rating": "EXCEPTIONAL", "ratingFraction": "EXCEPTIONAL"}, "utilizationConfidence": 27, "bioageConfidence": "HIGH", "sdnnBioAge": 64, "sdnnAgeDiff": -2, "sdnnRating": "GOOD", "rmssdBioAge": 66, "rmssdAgeDiff": 0, "rmssdRating": "GOOD", "hrBioAge": 56, "hrAgeDiff": -10, "hrRating": "EXCELLENT", "hrvBioAge": 52, "hrvAgeDiff": -14, "hrvRating": "EXCEPTIONAL", "pwfBioAge": 46, "pwfAgeDiff": -20, "pwfRating": "EXCEPTIONAL"}, "sleepAge": {"bioAge": 62, "bioAgeFraction": 62.45203062265629, "delta": -4, "deltaFraction": -3.547969377343712, "rating": "EXCEPTIONAL", "ratingFraction": "EXCEPTIONAL", "ageDiff": -4, "boost24": 89, "boostRating": "EXCEPTIONAL", "tst": {"bioAge": 64, "bioAgeFraction": 64.30549496599076, "delta": -2, "deltaFraction": -1.6945050340092394, "rating": "GOOD", "ratingFraction": "GOOD"}, "rem": {"bioAge": 64, "bioAgeFraction": 64.14653565666553, "delta": -2, "deltaFraction": -1.8534643433344655, "rating": "EXCELLENT", "ratingFraction": "EXCELLENT"}, "deep": {"bioAge": 67, "bioAgeFraction": 66.90341768007026, "delta": 1, "deltaFraction": 0.9034176800702625, "rating": "GOOD", "ratingFraction": "GOOD"}, "utilizationConfidence": 27, "bioageConfidence": "HIGH", "tstBioAge": 64, "tstAgeDiff": -2, "tstRating": "GOOD", "remSleepBioAge": 64, "remSleepAgeDiff": -2, "remRating": "EXCELLENT", "deepSleepBioAge": 67, "deepSleepAgeDiff": 1, "deepRating": "GOOD"}, "mentalAge": {"bioAge": 62, "bioAgeFraction": 62.398524682733154, "delta": -4, "deltaFraction": -3.6014753172668463, "rating": "EXCEPTIONAL", "ratingFraction": "EXCEPTIONAL", "ageDiff": -4, "boost24": 54, "boostRating": "GOOD", "rmssd": {"bioAge": 66, "bioAgeFraction": 65.61309060271027, "delta": 0, "deltaFraction": -0.3869093972897275, "rating": "GOOD", "ratingFraction": "EXCELLENT"}, "rem": {"bioAge": 63, "bioAgeFraction": 62.78543408002289, "delta": -3, "deltaFraction": -3.2145659199771117, "rating": "EXCEPTIONAL", "ratingFraction": "EXCEPTIONAL"}, "utilizationConfidence": 27, "bioageConfidence": "HIGH", "rmssdBioAge": 66, "rmssdAgeDiff": 0, "rmssdRating": "GOOD", "remBioAge": 63, "remAgeDiff": -3, "remRating": "EXCEPTIONAL"}}}]}